README.md
setup.cfg
setup.py
art_models/__init__.py
art_models/aegan.py
art_models/alexnet.py
art_models/bc_n.py
art_models/bc_x.py
art_models/c_512_multiclass_skip.py
art_models/c_512_multiclass_skip_finetune.py
art_models/c_512_multiclass_skip_v2.py
art_models/c_512_multiclass_skip_v2_finetune.py
art_models/c_multiclass_softmax_aggregate_cnf.py
art_models/chestxray.py
art_models/chestxray_cnf.py
art_models/chestxray_test.py
art_models/cifar10.py
art_models/cifar_cnf.py
art_models/densenet.py
art_models/eyepacs_cnf.py
art_models/fcn32_vgg.py
art_models/fcn8_vgg.py
art_models/forus_cnf.py
art_models/forus_finetune_v2.py
art_models/inception.py
art_models/inception_cnf.py
art_models/inception_cnf_128.py
art_models/inception_resnet.py
art_models/inception_resnetv2.py
art_models/inception_resnetv3.py
art_models/inception_resnetv3_2.py
art_models/inception_resnetv3_2_finetune.py
art_models/inception_v4.py
art_models/inception_v4_128.py
art_models/isbi_cnf.py
art_models/model_S.py
art_models/model_SD.py
art_models/model_c_cnf.py
art_models/model_n.py
art_models/model_n_2.py
art_models/model_n_chest.py
art_models/model_n_eyepacs.py
art_models/model_n_eyepacs_cnf.py
art_models/model_n_eyepacs_ft.py
art_models/model_n_eyepacs_test.py
art_models/model_n_test.py
art_models/model_z.py
art_models/model_z_global.py
art_models/model_z_v2.py
art_models/model_z_v3.py
art_models/multiclass_cnf.py
art_models/mura.py
art_models/mura_cnf.py
art_models/mura_cnf_2.py
art_models/mura_cnf_3.py
art_models/mura_global.py
art_models/mura_x.py
art_models/newtest.py
art_models/newtestv2.py
art_models/newtestv3.py
art_models/newtestv4.py
art_models/np.py
art_models/npt.py
art_models/npt_cnf.py
art_models/npt_cnf_2.py
art_models/npt_cnf_3.py
art_models/npt_test.py
art_models/qualcomm.py
art_models/resnet.py
art_models/resnet_utils.py
art_models/resnet_v1.py
art_models/resnet_v2.py
art_models/semi_supervised.py
art_models/semi_supervised_cnf.py
art_models/skip_256.py
art_models/skip_256_v1.py
tefla.egg-info/PKG-INFO
tefla.egg-info/SOURCES.txt
tefla.egg-info/dependency_links.txt
tefla.egg-info/requires.txt
tefla.egg-info/top_level.txt
