Metadata-Version: 1.1
Name: tefla
Version: 1.12.0
Summary: Simple end-to-end deep learning with tensorflow. Datasets,         data-augmentation, models, training, prediction, and metrics
Home-page: https://github.com/openAGI/tefla
Author: Tefla contributors
Author-email: mrinalhaloi11@gmail.com
License: MIT
Download-URL: https://github.com/openAGI/tefla/archive/1.12.0.zip
Keywords: tensorflow,deeplearning,cnn,deepcnn
Platform: linux
